CHANGES.md
LICENSE
Makefile
README.md
docs/Makefile
docs/changes.md
docs/conf.py
docs/index.md
docs/make.bat
docs/reference.md
docs/server.py
pyppeteer/__init__.py
pyppeteer/browser.py
pyppeteer/chromium_downloader.py
pyppeteer/command.py
pyppeteer/connection.py
pyppeteer/coverage.py
pyppeteer/dialog.py
pyppeteer/element_handle.py
pyppeteer/emulation_manager.py
pyppeteer/errors.py
pyppeteer/execution_context.py
pyppeteer/frame_manager.py
pyppeteer/helper.py
pyppeteer/input.py
pyppeteer/launcher.py
pyppeteer/multimap.py
pyppeteer/navigator_watcher.py
pyppeteer/network_manager.py
pyppeteer/options.py
pyppeteer/page.py
pyppeteer/page.py.orig
pyppeteer/target.py
pyppeteer/tracing.py
pyppeteer/us_keyboard_layout.py
pyppeteer/util.py
pyppeteer/worker.py
tests/__init__.py
tests/base.py
tests/blank_800x600.png
tests/closeme.py
tests/dumpio.py
tests/file-to-upload.txt
tests/frame_utils.py
tests/server.py
tests/test_abnormal_crash.py
tests/test_browser.py
tests/test_browser_context.py
tests/test_connection.py
tests/test_coverage.py
tests/test_dialog.py
tests/test_element_handle.py
tests/test_execution_context.py
tests/test_frame.py
tests/test_input.py
tests/test_launcher.py
tests/test_misc.py
tests/test_network.py
tests/test_page.py
tests/test_pyppeteer.py
tests/test_screenshot.py
tests/test_target.py
tests/test_tracing.py
tests/test_worker.py
tests/utils.py
pyppeteer2-0.2.2.dist-info/entry_points.txt
pyppeteer2-0.2.2.dist-info/LICENSE
pyppeteer2-0.2.2.dist-info/WHEEL
pyppeteer2-0.2.2.dist-info/METADATA
pyppeteer2-0.2.2.dist-info/RECORD
