Metadata-Version: 2.1
Name: pyppeteer2
Version: 0.2.2
Summary: Headless chrome/chromium automation library (unofficial port of puppeteer)
Home-page: https://github.com/pyppeteer/pyppeteer2
License: MIT
Keywords: pyppeteer,puppeteer,chrome,chromium
Author: pyppeteer
Author-email: pyppeteer@protonmail.com
Requires-Python: >=3.6.1,<4.0.0
Classifier: Development Status :: 3 - Alpha
Classifier: Intended Audience :: Developers
Classifier: License :: OSI Approved :: MIT License
Classifier: Natural Language :: English
Classifier: Programming Language :: Python :: 3
Classifier: Programming Language :: Python :: 3.6
Classifier: Programming Language :: Python :: 3.7
Classifier: Programming Language :: Python :: 3.8
Requires-Dist: appdirs (>=1.4.3,<2.0.0)
Requires-Dist: pyee (>=7.0.1,<8.0.0)
Requires-Dist: tqdm (>=4.42.1,<5.0.0)
Requires-Dist: urllib3 (>=1.25.8,<2.0.0)
Requires-Dist: websockets (>=8.1,<9.0)
Project-URL: Bug Tracker, https://github.com/pyppeteer/pyppeteer2/issues
Project-URL: Repository, https://github.com/pyppeteer/pyppeteer2
